modelcrafter/__init__.py
modelcrafter/data_masking.py
modelcrafter/grammarCorrection.py
modelcrafter/icd_code_generator.py
modelcrafter/imageGeneration.py
modelcrafter/main.py
modelcrafter/medical_scribing.py
modelcrafter/nl2sql.py
modelcrafter/pdfSummarizer.py
modelcrafter/productDescriptionGeneration.py
modelcrafter/query_csv.py
modelcrafter/rag_semantic_search.py
modelcrafter/structredExtraction.py
modelcrafter/summarizer.py
modelcrafter-0.0.4.dist-info/LICENSE
modelcrafter-0.0.4.dist-info/METADATA
modelcrafter-0.0.4.dist-info/WHEEL
modelcrafter-0.0.4.dist-info/dependency_links.txt
modelcrafter-0.0.4.dist-info/top_level.txt
modelcrafter-0.0.4.dist-info/RECORD
