Metadata-Version: 2.1
Name: modelcrafter
Version: 0.0.4
Summary: An avahiai library which makes your Gen-AI tasks effortless
Home-page: https://github.com/avahi-org/avahiplatform
Author: Avahi AWS
Author-email: info@avahitech.com
License: MIT
Classifier: License :: OSI Approved :: MIT License
Classifier: Programming Language :: Python :: 3.9
Classifier: Operating System :: OS Independent
Requires-Python: >=3.9
License-File: LICENSE
Requires-Dist: boto3 >=1.34.160
Requires-Dist: loguru >=0.7.2
Requires-Dist: python-docx >=1.1.2
Requires-Dist: PyMuPDF >=1.24.9
Requires-Dist: pandas ==2.0.0
Requires-Dist: numpy ==1.26.4
Requires-Dist: docutils >=0.21
Requires-Dist: langchain >=0.2.16
Requires-Dist: langchain-community >=0.2.16
Requires-Dist: langchain-experimental >=0.0.64
Requires-Dist: PyMySQL >=1.1.1
Requires-Dist: tabulate >=0.9.0
Requires-Dist: langchain-aws >=0.1.17
Requires-Dist: chromadb ==0.5.3
Requires-Dist: langchain-chroma >=0.1.3
Requires-Dist: unstructured >=0.12.3
Requires-Dist: unstructured[pdf]
Requires-Dist: pillow >=10.4.0
Requires-Dist: pytesseract >=0.3.8
Provides-Extra: dev
Requires-Dist: twine >=4.0.2 ; extra == 'dev'
Provides-Extra: pdf
Requires-Dist: unstructured[pdf] ; extra == 'pdf'
